PypptRoadSign/__init__.py
PypptRoadSign/background.py
PypptRoadSign/background_json.py
PypptRoadSign/sign.py
PypptRoadSign-0.1.1.dist-info/LICENSE
PypptRoadSign-0.1.1.dist-info/METADATA
PypptRoadSign-0.1.1.dist-info/WHEEL
PypptRoadSign-0.1.1.dist-info/top_level.txt
PypptRoadSign-0.1.1.dist-info/RECORD
